CHANGELOG.md
LICENSE
MANIFEST.in
README.md
setup.py
snide/__init__.py
snide/models.py
snide.egg-info/PKG-INFO
snide.egg-info/SOURCES.txt
snide.egg-info/dependency_links.txt
snide.egg-info/requires.txt
snide.egg-info/top_level.txt