Metadata-Version: 1.0
Name: snide
Version: 0.2.1
Summary: Snide: a remark.js parser in python
Home-page: https://github.com/michaeljoseph/snide
Author: Michael Joseph
Author-email: michaeljoseph@gmail.com
License: Apache License
